jambazid/demo/__init__.py
jambazid/demo/data/schema.json
jambazid/demo/module.py
jambazid/demo/py.typed
jambazid/demo/subpackage/__init__.py
jambazid/demo/subpackage/submodule.py
jambazid_logging-0.0.5.dist-info/METADATA
jambazid_logging-0.0.5.dist-info/WHEEL
jambazid_logging-0.0.5.dist-info/RECORD
