Metadata-Version: 2.3
Name: jambazid-logging
Version: 0.0.5
Summary: A minimal Python project template built with Poetry.
License: MIT
Author: Jambazid PyPI
Author-email: pypi@jambazid.dev
Maintainer: Jambazid PyPI
Maintainer-email: pypi@jambazid.dev
Requires-Python: >=3.11
Classifier: Development Status :: 2 - Pre-Alpha
Classifier: Topic :: Software Development :: Build Tools
Classifier: Topic :: Software Development :: Libraries :: Python Modules
Classifier: Topic :: Software Development :: Testing
Classifier: Topic :: Documentation
Project-URL: Bug Tracker, https://github.com/jambazid/python-poetry-template/issues
Project-URL: Homepage, https://poetry-demo.python.jambazid.dev
Project-URL: Repository, https://github.com/jambazid/python-poetry-template
